README.md
setup.py
beequants_sopt.egg-info/PKG-INFO
beequants_sopt.egg-info/SOURCES.txt
beequants_sopt.egg-info/dependency_links.txt
beequants_sopt.egg-info/requires.txt
beequants_sopt.egg-info/top_level.txt
sopt/__init__.py
sopt/GA/GA.py
sopt/GA/__init__.py
sopt/Optimizers/Gradients.py
sopt/Optimizers/Newton.py
sopt/Optimizers/RandomWalk.py
sopt/Optimizers/SA.py
sopt/Optimizers/__init__.py
sopt/PSO/PSO.py
sopt/PSO/__init__.py
sopt/SGA/SGA.py
sopt/SGA/__init__.py
sopt/test/__init__.py
sopt/test/test_AdaGrad.py
sopt/test/test_Adam.py
sopt/test/test_BFGS.py
sopt/test/test_DFP.py
sopt/test/test_GA.py
sopt/test/test_GradientDescent.py
sopt/test/test_Momentum.py
sopt/test/test_PSO.py
sopt/test/test_RMSProp.py
sopt/test/test_RandomWalk.py
sopt/test/test_SA.py
sopt/test/test_SGA.py
sopt/test/test_all.py
sopt/util/__init__.py
sopt/util/constraints.py
sopt/util/functions.py
sopt/util/ga_config.py
sopt/util/gradients_config.py
sopt/util/newton_config.py
sopt/util/pso_config.py
sopt/util/random_walk_config.py
sopt/util/sa_config.py
sopt/GA/GA.py
sopt/GA/__init__.py
sopt/Optimizers/Gradients.py
sopt/Optimizers/Newton.py
sopt/Optimizers/RandomWalk.py
sopt/Optimizers/SA.py
sopt/Optimizers/__init__.py
sopt/PSO/PSO.py
sopt/PSO/__init__.py
sopt/SGA/SGA.py
sopt/SGA/__init__.py
sopt/test/__init__.py
sopt/test/test_AdaGrad.py
sopt/test/test_Adam.py
sopt/test/test_BFGS.py
sopt/test/test_DFP.py
sopt/test/test_GA.py
sopt/test/test_GradientDescent.py
sopt/test/test_Momentum.py
sopt/test/test_PSO.py
sopt/test/test_RMSProp.py
sopt/test/test_RandomWalk.py
sopt/test/test_SA.py
sopt/test/test_SGA.py
sopt/test/test_all.py
sopt/util/__init__.py
sopt/util/constraints.py
sopt/util/functions.py
sopt/util/ga_config.py
sopt/util/gradients_config.py
sopt/util/newton_config.py
sopt/util/pso_config.py
sopt/util/random_walk_config.py
sopt/util/sa_config.py