Metadata-Version: 1.2
Name: beequants-sopt
Version: 0.0.1
Summary: sopt:a simple python optimizer library
Home-page: http://www.github.com/Lyrichu
Author: lyrichu
Author-email: 919987476@qq.com
Maintainer: lyrichu
Maintainer-email: 919987476@qq.com
License: UNKNOWN
Platform: UNKNOWN
